mailx/__init__.py
mailx/mailx.py
mailx-0.0.7.dist-info/LICENSE
mailx-0.0.7.dist-info/METADATA
mailx-0.0.7.dist-info/WHEEL
mailx-0.0.7.dist-info/top_level.txt
mailx-0.0.7.dist-info/RECORD
