Metadata-Version: 2.1
Name: mailx
Version: 0.0.7
Summary: make it easy to use mail
Home-page: https://gitee.com/ZeroSeeker/mailx
Author: ZeroSeeker
Author-email: zeroseeker@foxmail.com
Classifier: Programming Language :: Python :: 3
Classifier: Operating System :: OS Independent
License-File: LICENSE
Requires-Dist: envx (>=1.0.1)
